equilibrator/.DS_Store
equilibrator/__init__.py
equilibrator/flat/.DS_Store
equilibrator/flat/__init__.py
equilibrator/flat/equilibration.mdp
equilibrator/flat/equilibration_2.mdp
equilibrator/flat/ions.mdp
equilibrator/flat/minim.mdp
equilibrator/main.py
equilibrator/main.py~
equilibrator-0.1.2.dist-info/METADATA
equilibrator-0.1.2.dist-info/WHEEL
equilibrator-0.1.2.dist-info/entry_points.txt
equilibrator-0.1.2.dist-info/RECORD
